[{"q": "담보종목이 몇 개이고 무엇인가?", "cr": 1.0, "faith": 0.6666666666666666, "ac": 0.933837890625}, {"q": "입원의료비 보험가입금액의 최고한도는?", "cr": 1.0, "faith": 1.0, "ac": 0.9322509765625}, {"q": "표준형 입원의료비의 보상 비율(자기부담률)은?", "cr": 0.4, "faith": 0.6, "ac": 0.56787109375}, {"q": "선택형 입원의료비의 자기부담률은?", "cr": 0.2, "faith": 0.6, "ac": 0.9033203125}, {"q": "상급병실료 차액은 어떻게 보상하나?", "cr": 0.6666666666666666, "faith": 1.0, "ac": 0.9644775390625}, {"q": "하나의 상해로 인한 입원의료비 보상 기간은?", "cr": 1.0, "faith": 1.0, "ac": 0.934326171875}, {"q": "국민건강보험을 적용받지 못하는 경우 입원의료비 보상률은?", "cr": 1.0, "faith": 0.6, "ac": 0.1527099609375}, {"q": "상해통원 외래의료비의 연간 방문 한도는?", "cr": 1.0, "faith": 0.5, "ac": 0.9239501953125}, {"q": "통원 외래·약제의료비의 회(건)당 최고한도는?", "cr": 1.0, "faith": 1.0, "ac": 0.9097900390625}, {"q": "선택형 통원에서 상급종합병원(종합전문요양기관) 외래 공제금액은?", "cr": 0.2, "faith": 1.0, "ac": 0.10296630859375}, {"q": "선택형 통원에서 의원 외래 공제금액은?", "cr": 0.3, "faith": 1.0, "ac": 0.894287109375}, {"q": "통원 약제의료비(처방조제비)의 공제금액(선택형)은?", "cr": 0.3, "faith": 0.3, "ac": 0.8924560546875}, {"q": "표준형 통원에서 의원 외래 공제금액은?", "cr": 0.4, "faith": 1.0, "ac": 0.9149169921875}, {"q": "표준형 입원에서 자기부담 20%가 연간 250만원인 경우 실제 본인부담액은?", "cr": 0.6, "faith": 1.0, "ac": 0.17724609375}, {"q": "하나의 상해로 365일을 넘겨 입원할 경우 다시 보상받으려면?", "cr": 0.2, "faith": 1.0, "ac": 0.2020263671875}, {"q": "하루에 같은 상해로 2회 통원치료 시 공제는 어떻게 되나?", "cr": 0.2, "faith": 1.0, "ac": 0.9180908203125}, {"q": "임신·출산·산후기로 입원한 경우 보상되나?", "cr": 1.0, "faith": 0.3333333333333333, "ac": 0.5328369140625}, {"q": "비만(E66)으로 입원한 경우 보상되나?", "cr": 0.42857142857142855, "faith": 0.5, "ac": 0.145751953125}, {"q": "쌍꺼풀수술 등 외모 개선 목적 치료는 보상되나?", "cr": 1.0, "faith": 1.0, "ac": 0.10601806640625}, {"q": "해외 소재 의료기관에서 발생한 의료비는 보상되나?", "cr": 0.3, "faith": 1.0, "ac": 0.9385986328125}, {"q": "정신과질환 및 행동장애(F04~F99)로 입원 시 보상되나?", "cr": 1.0, "faith": 0.5, "ac": 0.6318359375}, {"q": "건강검진·예방접종·인공유산은 보상되나?", "cr": 0.3, "faith": 0.5, "ac": 0.46528320312500004}, {"q": "자동차보험이나 산재보험에서 보상받는 의료비는?", "cr": 1.0, "faith": 1.0, "ac": 0.5592041015625}, {"q": "피보험자의 정의는?", "cr": 1.0, "faith": 1.0, "ac": 0.955078125}, {"q": "실손의료비의 범위는?", "cr": 1.0, "faith": 1.0, "ac": 0.5584716796875}, {"q": "청약철회는 언제까지 가능한가?", "cr": 1.0, "faith": 1.0, "ac": 0.5828857421875}, {"q": "청약을 철회할 수 없는 계약은?", "cr": 0.5, "faith": 1.0, "ac": 0.8406110491071428}, {"q": "계약 취소는 언제까지 가능한가?", "cr": 0.21428571428571427, "faith": 1.0, "ac": 0.5506591796875}, {"q": "보험료 납입연체로 해지된 계약의 부활(효력회복) 청약 기간은?", "cr": 1.0, "faith": 1.0, "ac": 0.93212890625}, {"q": "보험금은 청구 후 언제까지 지급되나?", "cr": 1.0, "faith": 1.0, "ac": 0.9564208984375}, {"q": "통원 청구금액 3만원 이하인 경우 서류 제출은?", "cr": 1.0, "faith": 1.0, "ac": 0.1732177734375}, {"q": "이 실손의료비보험에서 정액 사망보험금이 지급되나?", "cr": 1.0, "faith": 1.0, "ac": 0.0992431640625}]